public class com.insanexs.mess.javap.JavapTest
  minor version: 0
  major version: 52
  flags: ACC_PUBLIC, ACC_SUPER
Constant pool:
   #1 = Methodref          #5.#30         // java/lang/Object."<init>":()V
   #2 = Fieldref           #4.#31         // com/insanexs/mess/javap/JavapTest.strField:Ljava/lang/String;
   #3 = Fieldref           #4.#32         // com/insanexs/mess/javap/JavapTest.intField:I
   #4 = Class              #33            // com/insanexs/mess/javap/JavapTest
   #5 = Class              #34            // java/lang/Object
   #6 = Utf8               VAR_CONSTANT
   #7 = Utf8               Ljava/lang/String;
   #8 = Utf8               ConstantValue
   #9 = String             #35            // CONSTANT
  #10 = Utf8               intField
  #11 = Utf8               I
  #12 = Utf8               intArraysField
  #13 = Utf8               [I
  #14 = Utf8               strField
  #15 = Utf8               <init>
  #16 = Utf8               ()V
  #17 = Utf8               Code
  #18 = Utf8               LineNumberTable
  #19 = Utf8               LocalVariableTable
  #20 = Utf8               this
  #21 = Utf8               Lcom/insanexs/mess/javap/JavapTest;
  #22 = Utf8               publicMethod
  #23 = Utf8               protectedReturnStrMethod
  #24 = Utf8               ()Ljava/lang/String;
  #25 = Utf8               privateSynchronizedMethod
  #26 = Utf8               (I)V
  #27 = Utf8               intArgs
  #28 = Utf8               SourceFile
  #29 = Utf8               JavapTest.java
  #30 = NameAndType        #15:#16        // "<init>":()V
  #31 = NameAndType        #14:#7         // strField:Ljava/lang/String;
  #32 = NameAndType        #10:#11        // intField:I
  #33 = Utf8               com/insanexs/mess/javap/JavapTest
  #34 = Utf8               java/lang/Object
  #35 = Utf8               CONSTANT
{
  protected static final java.lang.String VAR_CONSTANT;
    descriptor: Ljava/lang/String;
    flags: ACC_PROTECTED, ACC_STATIC, ACC_FINAL
    ConstantValue: String CONSTANT

  public com.insanexs.mess.javap.JavapTest();
    descriptor: ()V
    flags: ACC_PUBLIC
    Code:
      stack=1, locals=1, args_size=1
         0: aload_0
         1: invokespecial #1                  // Method java/lang/Object."<init>":()V
         4: return
      LineNumberTable:
        line 13: 0
        line 15: 4
      LocalVariableTable:
        Start  Length  Slot  Name   Signature
            0       5     0  this   Lcom/insanexs/mess/javap/JavapTest;

  public void publicMethod();
    descriptor: ()V
    flags: ACC_PUBLIC
    Code:
      stack=0, locals=1, args_size=1
         0: return
      LineNumberTable:
        line 19: 0
      LocalVariableTable:
        Start  Length  Slot  Name   Signature
            0       1     0  this   Lcom/insanexs/mess/javap/JavapTest;

  protected java.lang.String protectedReturnStrMethod();
    descriptor: ()Ljava/lang/String;
    flags: ACC_PROTECTED
    Code:
      stack=1, locals=1, args_size=1
         0: aload_0
         1: getfield      #2                  // Field strField:Ljava/lang/String;
         4: areturn
      LineNumberTable:
        line 22: 0
      LocalVariableTable:
        Start  Length  Slot  Name   Signature
            0       5     0  this   Lcom/insanexs/mess/javap/JavapTest;
}
SourceFile: "JavapTest.java"
